data_loader_xyz/__init__.py
data_loader_xyz/configs/__init__.py
data_loader_xyz/configs/base_config.py
data_loader_xyz/src/__init__.py
data_loader_xyz/src/mount.py
data_loader_xyz/utils/__init__.py
data_loader_xyz/utils/util.py
data_loader_xyz-0.0.6.dist-info/LICENCE
data_loader_xyz-0.0.6.dist-info/METADATA
data_loader_xyz-0.0.6.dist-info/WHEEL
data_loader_xyz-0.0.6.dist-info/entry_points.txt
data_loader_xyz-0.0.6.dist-info/top_level.txt
data_loader_xyz-0.0.6.dist-info/RECORD
