Metadata-Version: 2.1
Name: data-loader-xyz
Version: 0.0.6
Summary: to work with aws S3
Home-page: https://github.com/Proxia-ai/data_loader
Author: Zied
Author-email: ziedici@gmail.com
License: BSD
Project-URL: url0, https://github.com/Proxia-ai/
Keywords: working with aws S3
Classifier: Programming Language :: Python :: 3
Classifier: License :: OSI Approved :: MIT License
Classifier: Operating System :: OS Independent
Classifier: Topic :: Software Development :: Build Tools
Classifier: Development Status :: 3 - Alpha
Classifier: Intended Audience :: Developers
Classifier: Programming Language :: Python :: 3.7
Requires-Python: >=3.7
License-File: LICENCE
Requires-Dist: PyYAML
Requires-Dist: pandas
Requires-Dist: boto3
Requires-Dist: python-dotenv
